{
  "date": "2025-04-18",
  "title": "Trump campaign launches crypto-backed gift cards for donation bundling",
  "summary": "The Trump campaign debuted a system of prepaid donation gift cards tied to crypto wallets, enabling supporters to transfer campaign contributions in an indirect manner that skirts donor disclosure thresholds.",
  "tags": [
    "Donald Trump",
    "Campaign Finance Violations",
    "Crypto",
    "Disclosure Loopholes",
    "Ongoing"
  ],
  "sources": [
    "https://www.citizensforethics.org/reports-investigations/crew-investigations/trump-campaign-crypto-giftcards/"
  ]
}